pylambdic/__init__.py
pylambdic-1.0.0.dist-info/LICENSE
pylambdic-1.0.0.dist-info/METADATA
pylambdic-1.0.0.dist-info/WHEEL
pylambdic-1.0.0.dist-info/top_level.txt
pylambdic-1.0.0.dist-info/RECORD
