Metadata-Version: 2.1
Name: pylambdic
Version: 1.0.0
Summary: Validate input and output for AWS Lambda handlers using Pydantic
Home-page: https://github.com/agusmdev/pylambdic
Author: Agustin Marchi
Author-email: agusmdev@gmail.com
Classifier: Development Status :: 5 - Production/Stable
Classifier: Intended Audience :: Developers
Classifier: License :: OSI Approved :: MIT License
Classifier: Programming Language :: Python :: 3
Classifier: Programming Language :: Python :: 3.7
Classifier: Programming Language :: Python :: 3.8
Classifier: Programming Language :: Python :: 3.9
Classifier: Topic :: Software Development :: Libraries :: Python Modules
Requires-Python: >=3.7
License-File: LICENSE
Requires-Dist: pydantic (>=1.10.7)
